{
  "id": 1225023,
  "date": "2026-06-05T08:39:25",
  "date_gmt": "2026-06-05T12:39:25",
  "modified": "2026-06-05T08:39:25",
  "modified_gmt": "2026-06-05T12:39:25",
  "slug": "toi-3457",
  "type": "star",
  "link": "https://science.nasa.gov/exoplanets/star-catalog/toi-3457/",
  "featured_media": 429647,
  "categories": [],
  "acf": {
    "display_name": "TOI-3457",
    "custom_star_title": "",
    "aliases": "",
    "constellation": "Chamaeleon",
    "custom_star_description": "",
    "tagline": "",
    "pop_culture": "",
    "detection_timeline": "",
    "rv_planets_prospects": "",
    "transit_planets_prospects": "",
    "imaging_planets_prospects": "",
    "planet_ids": [
      1225105
    ],
    "exo_id": "TOI-3457",
    "st_optmag": 12.44,
    "st_vj": 12.44,
    "st_dist": 370.666,
    "st_j": 12.44,
    "st_mass": 1.04,
    "dec": -79.7572043,
    "st_teff": 6300,
    "st_rad": 1.474,
    "ra": 183.2082686,
    "system_radius": 29934533.787,
    "pl_hostname": "TOI-3457",
    "stellar_type": "F",
    "tic_id": "TIC 357312511",
    "magnitude": 12.44
  },
  "_links": {
    "self": [
      {
        "href": "https://science.nasa.gov/wp-json/wp/v2/star/1225023",
        "targetHints": {
          "allow": [
            "GET"
          ]
        }
      }
    ],
    "collection": [
      {
        "href": "https://science.nasa.gov/wp-json/wp/v2/star"
      }
    ],
    "about": [
      {
        "href": "https://science.nasa.gov/wp-json/wp/v2/types/star"
      }
    ],
    "acf:post": [
      {
        "embeddable": true,
        "href": "https://science.nasa.gov/wp-json/wp/v2/exoplanet/1225105"
      }
    ],
    "wp:featuredmedia": [
      {
        "embeddable": true,
        "href": "https://science.nasa.gov/wp-json/wp/v2/media/429647"
      }
    ]
  }
}