{
  "id": 260415,
  "date": "2023-11-28T20:25:30",
  "date_gmt": "2023-11-29T01:25:30",
  "modified": "2025-04-23T05:53:39",
  "modified_gmt": "2025-04-23T09:53:39",
  "slug": "hat-p-23",
  "type": "star",
  "link": "https://science.nasa.gov/exoplanets/star-catalog/hat-p-23/",
  "featured_media": 0,
  "categories": [],
  "acf": {
    "display_name": "HAT-P-23",
    "custom_star_title": "",
    "aliases": "",
    "constellation": "Delphinus",
    "custom_star_description": "",
    "tagline": "",
    "pop_culture": "",
    "detection_timeline": "",
    "rv_planets_prospects": "",
    "transit_planets_prospects": "",
    "imaging_planets_prospects": "",
    "planet_ids": [
      243738
    ],
    "exo_id": "HAT-P-23",
    "st_optmag": 11.937,
    "st_vj": 11.937,
    "st_dist": 364.813,
    "st_j": 11.937,
    "st_mass": 1.13,
    "dec": 16.7621462,
    "st_teff": 5905,
    "st_rad": 1.203,
    "ra": 306.1239076,
    "system_radius": 3470670.584,
    "pl_hostname": "HAT-P-23",
    "stellar_type": "G",
    "tic_id": "TIC 305243225",
    "magnitude": 11.937
  },
  "_links": {
    "self": [
      {
        "href": "https://science.nasa.gov/wp-json/wp/v2/star/260415",
        "targetHints": {
          "allow": [
            "GET"
          ]
        }
      }
    ],
    "collection": [
      {
        "href": "https://science.nasa.gov/wp-json/wp/v2/star"
      }
    ],
    "about": [
      {
        "href": "https://science.nasa.gov/wp-json/wp/v2/types/star"
      }
    ],
    "acf:post": [
      {
        "embeddable": true,
        "href": "https://science.nasa.gov/wp-json/wp/v2/exoplanet/243738"
      }
    ]
  }
}