{"id":262521,"date":"2023-11-28T20:52:03","date_gmt":"2023-11-29T01:52:03","modified":"2025-04-23T05:56:23","modified_gmt":"2025-04-23T09:56:23","slug":"hd_45350","type":"star","link":"https://science.nasa.gov/exoplanets/star-catalog/hd_45350/","featured_media":0,"categories":[],"acf":{"display_name":"HD 45350","custom_star_title":"","aliases":"","constellation":"Auriga","custom_star_description":"","tagline":"","pop_culture":"","detection_timeline":"","rv_planets_prospects":"","transit_planets_prospects":"","imaging_planets_prospects":"","planet_ids":[244452],"exo_id":"HD_45350","st_optmag":7.89,"st_vj":7.89,"st_dist":46.8733,"st_j":7.89,"st_mass":0.98,"dec":38.9627315,"st_teff":5566,"st_rad":1.26442,"ra":97.1902262,"system_radius":287227910.4,"pl_hostname":"HD_45350","stellar_type":"G","tic_id":"TIC 144132551","magnitude":7.89},"_links":{"self":[{"href":"https://science.nasa.gov/wp-json/wp/v2/star/262521","targetHints":{"allow":["GET"]}}],"collection":[{"href":"https://science.nasa.gov/wp-json/wp/v2/star"}],"about":[{"href":"https://science.nasa.gov/wp-json/wp/v2/types/star"}],"acf:post":[{"embeddable":true,"href":"https://science.nasa.gov/wp-json/wp/v2/exoplanet/244452"}]}}