{"id":263059,"date":"2023-11-28T20:58:54","date_gmt":"2023-11-29T01:58:54","modified":"2025-06-06T07:20:06","modified_gmt":"2025-06-06T11:20:06","slug":"toi-1431","type":"star","link":"https://science.nasa.gov/exoplanets/star-catalog/toi-1431/","featured_media":0,"categories":[],"acf":{"display_name":"TOI-1431","custom_star_title":"","aliases":"","constellation":"Cepheus","custom_star_description":"","tagline":"","pop_culture":"","detection_timeline":"","rv_planets_prospects":"","transit_planets_prospects":"","imaging_planets_prospects":"","planet_ids":[248452],"exo_id":"TOI-1431","st_optmag":8.03,"st_vj":8.03,"st_dist":148.925,"st_j":8.03,"st_mass":1.9,"dec":55.5880221,"st_teff":7690,"st_rad":1.92,"ra":316.2036922,"system_radius":6881502.02,"pl_hostname":"TOI-1431","stellar_type":"A","tic_id":"TIC 375506058","magnitude":8.03},"_links":{"self":[{"href":"https://science.nasa.gov/wp-json/wp/v2/star/263059","targetHints":{"allow":["GET"]}}],"collection":[{"href":"https://science.nasa.gov/wp-json/wp/v2/star"}],"about":[{"href":"https://science.nasa.gov/wp-json/wp/v2/types/star"}],"acf:post":[{"embeddable":true,"href":"https://science.nasa.gov/wp-json/wp/v2/exoplanet/248452"}]}}