{
  "id": 263356,
  "date": "2023-11-28T21:02:37",
  "date_gmt": "2023-11-29T02:02:37",
  "modified": "2025-04-23T05:55:11",
  "modified_gmt": "2025-04-23T09:55:11",
  "slug": "kepler-1020",
  "type": "star",
  "link": "https://science.nasa.gov/exoplanets/star-catalog/kepler-1020/",
  "featured_media": 0,
  "categories": [],
  "acf": {
    "display_name": "Kepler-1020",
    "custom_star_title": "",
    "aliases": "",
    "constellation": "Cygnus",
    "custom_star_description": "",
    "tagline": "",
    "pop_culture": "",
    "detection_timeline": "",
    "rv_planets_prospects": "",
    "transit_planets_prospects": "",
    "imaging_planets_prospects": "",
    "planet_ids": [
      245255
    ],
    "exo_id": "Kepler-1020",
    "st_optmag": 14.211,
    "st_vj": 14.211,
    "st_dist": 415.358,
    "st_j": 14.211,
    "st_mass": 0.87,
    "dec": 46.3772776,
    "st_teff": 5227,
    "st_rad": 0.8,
    "ra": 292.672471,
    "system_radius": 56239823.2478,
    "pl_hostname": "Kepler-1020",
    "stellar_type": "K",
    "tic_id": "TIC 63362217",
    "magnitude": 14.211
  },
  "_links": {
    "self": [
      {
        "href": "https://science.nasa.gov/wp-json/wp/v2/star/263356",
        "targetHints": {
          "allow": [
            "GET"
          ]
        }
      }
    ],
    "collection": [
      {
        "href": "https://science.nasa.gov/wp-json/wp/v2/star"
      }
    ],
    "about": [
      {
        "href": "https://science.nasa.gov/wp-json/wp/v2/types/star"
      }
    ],
    "acf:post": [
      {
        "embeddable": true,
        "href": "https://science.nasa.gov/wp-json/wp/v2/exoplanet/245255"
      }
    ]
  }
}