{"id":263604,"date":"2023-11-28T21:05:47","date_gmt":"2023-11-29T02:05:47","modified":"2025-06-06T07:19:02","modified_gmt":"2025-06-06T11:19:02","slug":"wasp-59","type":"star","link":"https://science.nasa.gov/exoplanets/star-catalog/wasp-59/","featured_media":0,"categories":[],"acf":{"display_name":"WASP-59","custom_star_title":"","aliases":"","constellation":"Pegasus","custom_star_description":"","tagline":"","pop_culture":"","detection_timeline":"","rv_planets_prospects":"","transit_planets_prospects":"","imaging_planets_prospects":"","planet_ids":[248876],"exo_id":"WASP-59","st_optmag":12.659,"st_vj":12.659,"st_dist":115.936,"st_j":12.659,"st_mass":0.719,"dec":24.889277,"st_teff":4650,"st_rad":0.613,"ra":349.6229547,"system_radius":10426971.539,"pl_hostname":"WASP-59","stellar_type":"K","tic_id":"TIC 91051152","magnitude":12.659},"_links":{"self":[{"href":"https://science.nasa.gov/wp-json/wp/v2/star/263604","targetHints":{"allow":["GET"]}}],"collection":[{"href":"https://science.nasa.gov/wp-json/wp/v2/star"}],"about":[{"href":"https://science.nasa.gov/wp-json/wp/v2/types/star"}],"acf:post":[{"embeddable":true,"href":"https://science.nasa.gov/wp-json/wp/v2/exoplanet/248876"}]}}