{
  "id": 391157,
  "date": "2024-04-30T20:00:51",
  "date_gmt": "2024-05-01T00:00:51",
  "modified": "2025-04-23T05:56:33",
  "modified_gmt": "2025-04-23T09:56:33",
  "slug": "toi-4559",
  "type": "star",
  "link": "https://science.nasa.gov/exoplanets/star-catalog/toi-4559/",
  "featured_media": 0,
  "categories": [],
  "acf": {
    "display_name": "TOI-4559",
    "custom_star_title": "",
    "aliases": "",
    "constellation": "Hydra",
    "custom_star_description": "",
    "tagline": "",
    "pop_culture": "",
    "detection_timeline": "",
    "rv_planets_prospects": "",
    "transit_planets_prospects": "",
    "imaging_planets_prospects": "",
    "planet_ids": [
      395663
    ],
    "exo_id": "TOI-4559",
    "st_optmag": 13.115,
    "st_vj": 13.115,
    "st_dist": 31.6354,
    "st_j": 13.115,
    "st_mass": 0.392,
    "dec": -30.0141252,
    "st_teff": 3558,
    "st_rad": 0.374,
    "ra": 211.0135378,
    "system_radius": 5370563.533,
    "pl_hostname": "TOI-4559",
    "stellar_type": "M",
    "tic_id": "TIC 271169413",
    "magnitude": 13.115
  },
  "_links": {
    "self": [
      {
        "href": "https://science.nasa.gov/wp-json/wp/v2/star/391157",
        "targetHints": {
          "allow": [
            "GET"
          ]
        }
      }
    ],
    "collection": [
      {
        "href": "https://science.nasa.gov/wp-json/wp/v2/star"
      }
    ],
    "about": [
      {
        "href": "https://science.nasa.gov/wp-json/wp/v2/types/star"
      }
    ],
    "acf:post": [
      {
        "embeddable": true,
        "href": "https://science.nasa.gov/wp-json/wp/v2/exoplanet/395663"
      }
    ]
  }
}