{
  "id": 401560,
  "date": "2024-06-13T20:50:22",
  "date_gmt": "2024-06-14T00:50:22",
  "modified": "2025-04-23T05:53:50",
  "modified_gmt": "2025-04-23T09:53:50",
  "slug": "toi-128",
  "type": "star",
  "link": "https://science.nasa.gov/exoplanets/star-catalog/toi-128/",
  "featured_media": 0,
  "categories": [],
  "acf": {
    "display_name": "TOI-128",
    "custom_star_title": "",
    "aliases": "",
    "constellation": "Mensa",
    "custom_star_description": "",
    "tagline": "",
    "pop_culture": "",
    "detection_timeline": "",
    "rv_planets_prospects": "",
    "transit_planets_prospects": "",
    "imaging_planets_prospects": "",
    "planet_ids": [
      401598
    ],
    "exo_id": "TOI-128",
    "st_optmag": 8.44,
    "st_vj": 8.44,
    "st_dist": 68.4727,
    "st_j": 8.44,
    "st_mass": 0.851969,
    "dec": -80.964384,
    "st_teff": 6086,
    "st_rad": 1.13,
    "ra": 79.5209381,
    "system_radius": 8049889.8082953,
    "pl_hostname": "TOI-128",
    "stellar_type": "F",
    "tic_id": "TIC 391949880",
    "magnitude": 8.44
  },
  "_links": {
    "self": [
      {
        "href": "https://science.nasa.gov/wp-json/wp/v2/star/401560",
        "targetHints": {
          "allow": [
            "GET"
          ]
        }
      }
    ],
    "collection": [
      {
        "href": "https://science.nasa.gov/wp-json/wp/v2/star"
      }
    ],
    "about": [
      {
        "href": "https://science.nasa.gov/wp-json/wp/v2/types/star"
      }
    ],
    "acf:post": [
      {
        "embeddable": true,
        "href": "https://science.nasa.gov/wp-json/wp/v2/exoplanet/401598"
      }
    ]
  }
}