{
  "id": 245592,
  "date": "2017-10-02T13:32:50",
  "date_gmt": "2017-10-02T17:32:50",
  "modified": "2025-03-28T07:30:00",
  "modified_gmt": "2025-03-28T11:30:00",
  "slug": "kepler-1259-b",
  "type": "exoplanet",
  "link": "https://science.nasa.gov/exoplanet-catalog/kepler-1259-b/",
  "featured_media": 271833,
  "categories": [
    2014,
    2013
  ],
  "acf": {
    "pl_hostname": "Kepler-1259",
    "pl_letter": "b",
    "display_name": "Kepler-1259 b",
    "planet_radius": "1.43 x Earth",
    "derived_description": "Kepler-1259 b is a super Earth exoplanet that orbits a K-type star. Its mass is 2.63 Earths, it takes 0.7 days to complete one orbit of its star, and is 0.0141 AU from its star. Its discovery was announced in 2016.",
    "planet_type": "Super Earth",
    "pl_discmethod": "Transit",
    "pl_facility": "Kepler",
    "st_dist": 805.562,
    "planet_mass": "2.63 Earths",
    "st_optmag": 15.556,
    "discovery_date": "2016",
    "pl_orbsmax": 0.0141,
    "period_display": "0.7 days",
    "eccentricity": "0.0",
    "star_id": 261385,
    "pl_orbper": 0.663085258,
    "pl_kepflag": true,
    "pl_radj": 0.12757605,
    "pl_disc": 2016,
    "pl_publ_date": "2016",
    "planet_orbit_period": "",
    "multiple_planet_system": false,
    "pl_rade": 1.43,
    "exo_id": "Kepler-1259_b",
    "planet_size_class": "super-Terrestrial",
    "pl_eccenlim": 0,
    "pl_orbeccen": 0
  },
  "_links": {
    "self": [
      {
        "href": "https://science.nasa.gov/wp-json/wp/v2/exoplanet/245592",
        "targetHints": {
          "allow": [
            "GET"
          ]
        }
      }
    ],
    "collection": [
      {
        "href": "https://science.nasa.gov/wp-json/wp/v2/exoplanet"
      }
    ],
    "about": [
      {
        "href": "https://science.nasa.gov/wp-json/wp/v2/types/exoplanet"
      }
    ],
    "acf:post": [
      {
        "embeddable": true,
        "href": "https://science.nasa.gov/wp-json/wp/v2/star/261385"
      }
    ],
    "wp:featuredmedia": [
      {
        "embeddable": true,
        "href": "https://science.nasa.gov/wp-json/wp/v2/media/271833"
      }
    ]
  }
}