{
  "id": 247056,
  "date": "2017-10-02T13:32:37",
  "date_gmt": "2017-10-02T17:32:37",
  "modified": "2025-07-07T17:55:38",
  "modified_gmt": "2025-07-07T21:55:38",
  "slug": "kepler-360-c",
  "type": "exoplanet",
  "link": "https://science.nasa.gov/exoplanet-catalog/kepler-360-c/",
  "featured_media": 267560,
  "categories": [
    2014,
    2013
  ],
  "acf": {
    "pl_hostname": "Kepler-360",
    "pl_letter": "c",
    "display_name": "Kepler-360 c",
    "planet_radius": "2.1 x Earth",
    "derived_description": "Kepler-360 c is a Neptune-like exoplanet that orbits a F-type star. Its mass is 5.06 Earths, it takes 7.2 days to complete one orbit of its star, and is 0.075 AU from its star. Its discovery was announced in 2014.",
    "planet_type": "Neptune-like",
    "pl_discmethod": "Transit",
    "pl_facility": "Kepler",
    "st_dist": 876.044,
    "planet_mass": "5.06 Earths",
    "st_optmag": 15.011,
    "discovery_date": "2014",
    "pl_orbsmax": 0.075,
    "period_display": "7.2 days",
    "eccentricity": "0.0",
    "star_id": 263455,
    "pl_orbper": 7.186434,
    "pl_kepflag": true,
    "pl_radj": 0.187,
    "pl_disc": 2014,
    "pl_publ_date": "2014",
    "planet_orbit_period": "",
    "multiple_planet_system": false,
    "pl_rade": 2.1,
    "exo_id": "Kepler-360_c",
    "planet_size_class": "sub-Neptunian",
    "pl_eccenlim": 0,
    "pl_orbeccen": 0
  },
  "_links": {
    "self": [
      {
        "href": "https://science.nasa.gov/wp-json/wp/v2/exoplanet/247056",
        "targetHints": {
          "allow": [
            "GET"
          ]
        }
      }
    ],
    "collection": [
      {
        "href": "https://science.nasa.gov/wp-json/wp/v2/exoplanet"
      }
    ],
    "about": [
      {
        "href": "https://science.nasa.gov/wp-json/wp/v2/types/exoplanet"
      }
    ],
    "acf:post": [
      {
        "embeddable": true,
        "href": "https://science.nasa.gov/wp-json/wp/v2/star/263455"
      }
    ],
    "wp:featuredmedia": [
      {
        "embeddable": true,
        "href": "https://science.nasa.gov/wp-json/wp/v2/media/267560"
      }
    ]
  }
}