{"id":248407,"date":"2020-04-03T13:27:00","date_gmt":"2020-04-03T17:27:00","modified":"2025-07-07T20:38:50","modified_gmt":"2025-07-08T00:38:50","slug":"toi-1130-b","type":"exoplanet","link":"https://science.nasa.gov/exoplanet-catalog/toi-1130-b/","featured_media":267560,"categories":[2014,2013],"acf":{"pl_hostname":"TOI-1130","pl_letter":"b","display_name":"TOI-1130 b","planet_radius":"0.32652389 x Jupiter","derived_description":"TOI-1130 b is a Neptune-like exoplanet that orbits a K-type star. Its mass is 19.8 Earths, it takes 4.1 days to complete one orbit of its star, and is 0.0453 AU from its star. Its discovery was announced in 2020.","planet_type":"Neptune-like","pl_discmethod":"Transit","pl_facility":"Transiting Exoplanet Survey Satellite (TESS)","st_dist":58.2609,"planet_mass":"19.8 Earths","st_optmag":11.595,"discovery_date":"2020","pl_orbsmax":0.0453,"period_display":"4.1 days","eccentricity":"0.05","star_id":262696,"pl_orbper":4.074554,"pl_kepflag":false,"pl_radj":0.32652389,"pl_disc":2020,"pl_publ_date":"2020","planet_orbit_period":141.11,"multiple_planet_system":false,"pl_rade":3.66,"exo_id":"TOI-1130_b","planet_size_class":"Neptunian","pl_eccenlim":0,"pl_orbeccen":0.052162},"_links":{"self":[{"href":"https://science.nasa.gov/wp-json/wp/v2/exoplanet/248407","targetHints":{"allow":["GET"]}}],"collection":[{"href":"https://science.nasa.gov/wp-json/wp/v2/exoplanet"}],"about":[{"href":"https://science.nasa.gov/wp-json/wp/v2/types/exoplanet"}],"acf:post":[{"embeddable":true,"href":"https://science.nasa.gov/wp-json/wp/v2/star/262696"}],"wp:featuredmedia":[{"embeddable":true,"href":"https://science.nasa.gov/wp-json/wp/v2/media/267560"}]}}