{
  "id": 313832,
  "date": "2024-02-23T16:01:22",
  "date_gmt": "2024-02-23T21:01:22",
  "modified": "2025-07-07T15:25:44",
  "modified_gmt": "2025-07-07T19:25:44",
  "slug": "hd-134606-d",
  "type": "exoplanet",
  "link": "https://science.nasa.gov/exoplanet-catalog/hd-134606-d/",
  "featured_media": 271855,
  "categories": [
    2014,
    2013
  ],
  "acf": {
    "pl_hostname": "HD_134606",
    "pl_letter": "d",
    "display_name": "HD 134606 d",
    "planet_radius": "0.677 x Jupiter (estimate)",
    "derived_description": "HD 134606 d is a gas giant exoplanet that orbits a G-type star. Its mass is 0.14095656 Jupiters, it takes 2.6 years to complete one orbit of its star, and is 1.941 AU from its star. Its discovery was announced in 2024.",
    "planet_type": "Gas Giant",
    "pl_discmethod": "Radial Velocity",
    "pl_facility": "Multiple Observatories",
    "st_dist": 26.7909,
    "planet_mass": "0.14095656 Jupiters",
    "st_optmag": 6.86,
    "discovery_date": "2024",
    "pl_orbsmax": 1.941,
    "period_display": "2.6 years",
    "eccentricity": "0.09",
    "star_id": 313784,
    "pl_orbper": 966.5,
    "pl_kepflag": false,
    "pl_radj": 0.677,
    "pl_disc": 2024,
    "pl_publ_date": "2024",
    "planet_orbit_period": 194,
    "multiple_planet_system": false,
    "pl_rade": 7.59,
    "exo_id": "HD_134606_d",
    "planet_size_class": "sub-Jovian",
    "pl_eccenlim": 0,
    "pl_orbeccen": 0.092
  },
  "_links": {
    "self": [
      {
        "href": "https://science.nasa.gov/wp-json/wp/v2/exoplanet/313832",
        "targetHints": {
          "allow": [
            "GET"
          ]
        }
      }
    ],
    "collection": [
      {
        "href": "https://science.nasa.gov/wp-json/wp/v2/exoplanet"
      }
    ],
    "about": [
      {
        "href": "https://science.nasa.gov/wp-json/wp/v2/types/exoplanet"
      }
    ],
    "acf:post": [
      {
        "embeddable": true,
        "href": "https://science.nasa.gov/wp-json/wp/v2/star/313784"
      }
    ],
    "wp:featuredmedia": [
      {
        "embeddable": true,
        "href": "https://science.nasa.gov/wp-json/wp/v2/media/271855"
      }
    ]
  }
}