{
  "id": 404207,
  "date": "2024-06-27T21:57:41",
  "date_gmt": "2024-06-28T01:57:41",
  "modified": "2025-07-07T15:23:14",
  "modified_gmt": "2025-07-07T19:23:14",
  "slug": "tic-365102760-b",
  "type": "exoplanet",
  "link": "https://science.nasa.gov/exoplanet-catalog/tic-365102760-b/",
  "featured_media": 271833,
  "categories": [
    2014,
    2013
  ],
  "acf": {
    "pl_hostname": "TIC_365102760",
    "pl_letter": "b",
    "display_name": "TIC 365102760 b",
    "planet_radius": "0.55402005 x Jupiter",
    "derived_description": "TIC 365102760 b is a Neptune-like exoplanet that orbits a K-type star. Its mass is 19.2 Earths, it takes 4.2 days to complete one orbit of its star, and is 0.0622 AU from its star. Its discovery was announced in 2024.",
    "planet_type": "Neptune-like",
    "pl_discmethod": "Transit",
    "pl_facility": "Transiting Exoplanet Survey Satellite (TESS)",
    "st_dist": 555.546,
    "planet_mass": "19.2 Earths",
    "st_optmag": 12.154,
    "discovery_date": "2024",
    "pl_orbsmax": 0.0622,
    "period_display": "4.2 days",
    "eccentricity": "< 0.406",
    "star_id": 404190,
    "pl_orbper": 4.21285367,
    "pl_kepflag": false,
    "pl_radj": 0.55402005,
    "pl_disc": 2024,
    "pl_publ_date": "2024",
    "planet_orbit_period": 0.216,
    "multiple_planet_system": false,
    "pl_rade": 6.21,
    "exo_id": "TIC_365102760_b",
    "planet_size_class": "Neptunian",
    "pl_eccenlim": 0.406,
    "pl_orbeccen": 0
  },
  "_links": {
    "self": [
      {
        "href": "https://science.nasa.gov/wp-json/wp/v2/exoplanet/404207",
        "targetHints": {
          "allow": [
            "GET"
          ]
        }
      }
    ],
    "collection": [
      {
        "href": "https://science.nasa.gov/wp-json/wp/v2/exoplanet"
      }
    ],
    "about": [
      {
        "href": "https://science.nasa.gov/wp-json/wp/v2/types/exoplanet"
      }
    ],
    "acf:post": [
      {
        "embeddable": true,
        "href": "https://science.nasa.gov/wp-json/wp/v2/star/404190"
      }
    ],
    "wp:featuredmedia": [
      {
        "embeddable": true,
        "href": "https://science.nasa.gov/wp-json/wp/v2/media/271833"
      }
    ]
  }
}